portia2code/__init__.py
portia2code/parser.py
portia2code/porter.py
portia2code/processors.py
portia2code/samples.py
portia2code/spiders.py
portia2code/starturls.py
portia2code/templates.py
portia2code/utils.py
portia2code-0.0.17.data/scripts/portia_porter
portia2code-0.0.17.dist-info/DESCRIPTION.rst
portia2code-0.0.17.dist-info/METADATA
portia2code-0.0.17.dist-info/RECORD
portia2code-0.0.17.dist-info/WHEEL
portia2code-0.0.17.dist-info/metadata.json
portia2code-0.0.17.dist-info/top_level.txt
