Metadata-Version: 2.0
Name: portia2code
Version: 0.0.17
Summary: Convert portia spider definitions to python scrapy spiders
Home-page: https://github.com/scrapinghub/portia2code
Author: Scrapinghub
Author-email: info@scrapinghub.com
Maintainer: Ruairi Fahy
Maintainer-email: ruairi@scrapinghub.com
License: BSD
Download-URL: https://github.com/scrapinghub/portia2code/tarball/portia2code-0.0.17
Platform: Any
Classifier: Development Status :: 4 - Beta
Classifier: License :: OSI Approved :: BSD License
Classifier: Operating System :: OS Independent
Classifier: Programming Language :: Python
Classifier: Programming Language :: Python :: 2
Classifier: Programming Language :: Python :: 2.7
Requires-Dist: Scrapy
Requires-Dist: slybot (>=0.13.0)
Requires-Dist: dateparser
Requires-Dist: six (==1.10.0)
Requires-Dist: w3lib
Requires-Dist: scrapely
Requires-Dist: autoflake (==0.6.6)
Requires-Dist: autopep8 (==1.2.2)
